yingmi/yaml/__init__.py
yingmi/yaml/nested_dict_value.py
yingmi/yaml/variables.py
yingmi/yaml/yaml_parse.py
YingMiYAML-1.0.3.dist-info/LICENSE
YingMiYAML-1.0.3.dist-info/METADATA
YingMiYAML-1.0.3.dist-info/WHEEL
YingMiYAML-1.0.3.dist-info/top_level.txt
YingMiYAML-1.0.3.dist-info/RECORD
