Metadata-Version: 2.1
Name: YingMiYAML
Version: 1.0.3
Summary: UNKNOWN
Home-page: https://www.yingmi.cn
Author: liuyunfeng
Author-email: liuyf@yingmi.cn
License: UNKNOWN
Project-URL: Source Code, https://www.yingmi.cn
Platform: UNKNOWN
Classifier: Programming Language :: Python :: 3
Classifier: License :: OSI Approved :: MIT License
Classifier: Operating System :: OS Independent
Requires-Python: >3.6
License-File: LICENSE
Requires-Dist: PyYAML (==5.4.1)
